dailypics/__init__.py
dailypics/config.py
dailypics-1.0.0.dist-info/METADATA
dailypics-1.0.0.dist-info/WHEEL
dailypics-1.0.0.dist-info/top_level.txt
dailypics-1.0.0.dist-info/RECORD
