Metadata-Version: 2.1
Name: dailypics
Version: 1.0.0
Summary: A python library to obtain daily images from Unplash
Home-page: https://github.com/Wingwaresoftware/dailypic/
Author: Wingware
Author-email: wingwaresoftware@gmail.com
Classifier: Programming Language :: Python :: 3
Classifier: License :: OSI Approved :: MIT License
Classifier: Operating System :: OS Independent
Requires-Dist: requests
